MANIFEST.in
README.rst
setup.cfg
setup.py
django_web_crawler.egg-info/PKG-INFO
django_web_crawler.egg-info/SOURCES.txt
django_web_crawler.egg-info/dependency_links.txt
django_web_crawler.egg-info/requires.txt
django_web_crawler.egg-info/top_level.txt
gatherlinks/__init__.py
gatherlinks/admin.py
gatherlinks/apps.py
gatherlinks/models.py
gatherlinks/tests.py
gatherlinks/urls.py
gatherlinks/views.py
gatherlinks/crawler/__init__.py
gatherlinks/crawler/domain.py
gatherlinks/crawler/link_finder.py
gatherlinks/crawler/main.py
gatherlinks/crawler/spider.py
gatherlinks/migrations/__init__.py