Metadata-Version: 2.1
Name: django-web-crawler
Version: 0.9
Summary: A Django app to gather the links of a website.
Home-page: https://www.majestylink.com/
Author: Atuh Samuel
Author-email: atuhsamuel96@gmail.com
Maintainer: Atuh Samuel
Maintainer-email: atuhsamuel96@gmail.com
License: MIT
Platform: UNKNOWN
Classifier: Environment :: Web Environment
Classifier: Framework :: Django
Classifier: Framework :: Django :: 4.0
Classifier: Intended Audience :: Developers
Classifier: License :: OSI Approved :: BSD License
Classifier: Operating System :: OS Independent
Classifier: Programming Language :: Python
Classifier: Programming Language :: Python :: 3
Classifier: Programming Language :: Python :: 3 :: Only
Classifier: Programming Language :: Python :: 3.8
Classifier: Programming Language :: Python :: 3.9
Classifier: Topic :: Internet :: WWW/HTTP
Classifier: Topic :: Internet :: WWW/HTTP :: Dynamic Content
Requires-Python: >=3.8
